Workbook
Name AUD: Inputs!$B$4
Name Base_AISC: Inputs!$B$9
Name Capex_Index: CostDecomp!$F$10
Name Consumables_Index: CostDecomp!$F$7
Name Cost_Conf: Inputs!$B$13
Name CPI: Inputs!$B$6
Name Diesel_Price: CostDecomp!$F$4
Name FCF: Inputs!$B$23
Name Fed: Inputs!$B$3
Name Gold_USD: Inputs!$B$5
Name Grade_Recon: Inputs!$B$11
Name Jurisdiction: Inputs!$B$14
Name Margin: Inputs!$B$22
Name Power_Price: CostDecomp!$F$6
Name Prod_Oz: Inputs!$B$10
Name RBA: Inputs!$B$2
Name Recovery_Adj: Inputs!$B$12
Name Wage_Index: CostDecomp!$F$3

Sheet Inputs
A1: MACRO INPUTS
A2: RBA Rate | B2: 0.0385
A3: Fed Rate | B3: 0.03625
A4: AUD/USD | B4: 0.735
A5: Gold USD/oz | B5: 4496
A6: CPI Annual % | B6: 0.038
A8: MINE PARAMETERS
A9: Basic AISC (A$/oz) | B9: 2400
A10: Production (oz) | B10: 1000
A11: Grade Reconciliation | B11: 0.68
A12: Recovery Adjustment | B12: 0.95
A13: Cost Confidence | B13: 1
A14: Jurisdiction Probability | B14: 1
A17: DERIVED OUTPUTS
A18: Gold AUD/oz | B18: =+Gold_USD/AUD -> 6117.0068
A19: Rate Spread | B19: =+RBA-Fed -> 0.00225
A20: AISC Adjusted | B20: =+Base_AISC*Cost_Conf*(1+(CPI-0.025)) -> 2431.2
A21: Adj Production (oz) | B21: =+Prod_Oz*Grade_Recon*Recovery_Adj -> 646
A22: Margin (A$/oz) | B22: =+B18-B20 -> 3685.8068
A23: Annual FCF (A$) | B23: =+B22*B21*Jurisdiction -> 2381031.2

Sheet Sensitivity
A1: PARTIAL DERIVATIVES
A2: Variable | B2: ∂Margin/∂x | C2: Units | D2: Interpretation
A3: Gold USD/oz | B3: =1/AUD -> 1.3605442 | C3: A$ margin per US $1 gold | D3: Each US$1 rise in gold adds to this margin
A4: AUD/USD | B4: =+-Gold_USD/(AUD^2) -> -8322.4582 | C4: A$ margin per 0.01 AUD | D4: Negative = AUD Strength hurts margin for Aus co's
A5: CPI | B5: =+-Base_AISC*Cost_Conf -> -2400 | C5: A$ margin per 1pp CPI | D5: Higher inflation raises costs
A6: Base AISC | B6: =+-Cost_Conf*(1+(CPI-Inputs!B19)) -> -1.03575 | C6: A$ margin per A$1 AISC | D6: Higher base cost = lower margin
A7: Cost confidence | B7: =-Base_AISC*(1+(CPI-Inputs!B19)) -> -2485.8 | C7: A$ margin per 0.01 confidence | D7: Increasing multiplier raises adj AISC
A8: Grade reconciliation | B8: =+Margin*Prod_Oz*Recovery_Adj*Jurisdiction -> 3501516.5 | C8: A$ FCF per 0.01 grade recon | D8: Scales production proportionally
A9: Jurisdiction Prob | B9: =+Margin*Prod_Oz*Grade_Recon*Recovery_Adj -> 2381031.2 | C9: A$ FCF per 0.01 jurisdiction | D9: Probability weight on total FCF
A12: ELASTICITY ANALYSIS
A13: Variable | B13: Elasticity | C13: Rank | D13: Meaning | E13: ABS
A14: Gold USD | B14: =+B3*(Gold_USD/Margin) -> 1.6596113 | C14: =+RANK(E14,$E$14:$E$20,0) -> 2 | D14: If elasticity is 1.4 that means a 1% change in the input causes a 1.4% change in the output | E14: =+ABS(B14) -> 1.6596113
A15: AUD/USD | B15: =+B4*(AUD/Margin) -> -1.6596113 | C15: =+RANK(E15,$E$14:$E$20,0) -> 1 | E15: =+ABS(B15) -> 1.6596113
A16: CPI | B16: =+B5*(CPI/Margin) -> -0.024743565 | C16: =+RANK(E16,$E$14:$E$20,0) -> 7 | E16: =+ABS(B16) -> 0.024743565
A17: Base AISC | B17: =+B6*(Base_AISC/Margin) -> -0.67442493 | C17: =+RANK(E17,$E$14:$E$20,0) -> 5 | E17: =+ABS(B17) -> 0.67442493
A18: Cost Confidence | B18: =+B7*(Cost_Conf/Margin) -> -0.67442493 | C18: =+RANK(E18,$E$14:$E$20,0) -> 5 | E18: =+ABS(B18) -> 0.67442493
A19: Grade Reconciliation | B19: =+B8*(Grade_Recon/FCF) -> 1 | C19: =+RANK(E19,$E$14:$E$20,0) -> 4 | E19: =+ABS(B19) -> 1
A20: Jurisdiction | B20: =+B9*(Jurisdiction/FCF) -> 1 | C20: =+RANK(E20,$E$14:$E$20,0) -> 3 | E20: =+ABS(B20) -> 1
A23: DOLLAR IMPACT - REALISTIC MOVES
A24: Variable | B24: Realistic Move | C24: Margin Impact (A$/oz) | D24: Annual FCF Impact (A$)
A25: Gold + US$200 | B25: 200 | C25: =+B3*B25 -> 272.10884 | D25: =+C25*Inputs!B21*Jurisdiction -> 175782.31
A26: Gold - US$200 | B26: -200 | C26: =+B3*(B26) -> -272.10884 | D26: =+C26*Inputs!B21*Jurisdiction -> -175782.31
A27: AUD + 0.03 | B27: 0.03 | C27: =+B4*(B27) -> -249.67375 | D27: =+C27*Inputs!$B$21*Jurisdiction -> -161289.24
A28: AUD - 0.03 | B28: -0.03 | C28: =+B4*(B28) -> 249.67375 | D28: =+C28*Inputs!$B$21*Jurisdiction -> 161289.24
A29: CPI + 1pp | B29: 0.01 | C29: =+B5*B29 -> -24 | D29: =+C29*Inputs!B21*Jurisdiction -> -15504
A30: Grade Recon 0.90 | B30: -0.1 | C30: N/A affects production | D30: =+B8*B30 -> -350151.65
A31: Grade Recon 0.75 | B31: -0.25 | C31: N/A affects production | D31: =+B8*(B31) -> -875379.12
A34: CONVEXITY - SECOND DERIVATIVES
A35: ∂²Margin/∂AUD² | B35: =2*Gold_USD/(AUD^3) -> 22646.145
A36: Interpretation | B36: Positive = convex. AUD weakness helps more than AUD strength hurts by the same amount
A38: Convexity Test
A39: Margin if AUD falls 0.03 | B39: =+Gold_USD/(AUD-0.03)-Base_AISC*Cost_Conf*(1+(CPI-0.025)) -> 3946.105
A40: Margin if AUD rises 0.03 | B40: =+Gold_USD/(AUD+0.03)-Base_AISC*Cost_Conf*(1+(CPI-0.025)) -> 3445.9242
A41: Current margin | B41: =+Margin -> 3685.8068
A42: Gain from fall | B42: =+B39-B41 -> 260.29816
A43: Loss from rise | B43: =+B40-B41 -> -239.88262
A44: Asymmetry (A$/oz) | B44: =+B42+B43 -> 20.415542

Sheet CostDecomp
A1: AISC DECOMPOSITION
A2: Component | B2: Base A$/oz | C2: % of AISC | D2: Cost Driver | E2: Driver Base Value | F2: Driver Current Value | G2: Component Inflation | H2: Adjusted A$/oz
A3: Mining (Labour + equipment) | B3: 770 | C3: =+B3/SUM($B$3:$B$8,$B$10:$B$11) -> 0.36666667 | D3: WA Mining Wage Index | E3: 100 | F3: 100 | G3: =+(F3-E3)/E3 -> 0
A4: Mining Energy (diesel) | B4: 220 | C4: =+B4/SUM($B$3:$B$8,$B$10:$B$11) -> 0.1047619 | D4: Diesel A$/L | E4: 1.85 | F4: 1.85 | G4: =+(F4-E4)/E4 -> 0
A5: Processing Labour | B5: 200 | C5: =+B5/SUM($B$3:$B$8,$B$10:$B$11) -> 0.095238095 | D5: WA Mining Wage Index | E5: 100 | F5: 100 | G5: =+(F5-E5)/E5 -> 0
A6: Processing Energy (power) | B6: 180 | C6: =+B6/SUM($B$3:$B$8,$B$10:$B$11) -> 0.085714286 | D6: Electricity A$/MWh | E6: 85 | F6: 85 | G6: =+(F6-E6)/E6 -> 0
A7: Reagents & Consumables | B7: 130 | C7: =+B7/SUM($B$3:$B$8,$B$10:$B$11) -> 0.061904762 | D7: Consumables Index | E7: 100 | F7: 100 | G7: =+(F7-E7)/E7 -> 0
A8: Site G&A | B8: 180 | C8: =+B8/SUM($B$3:$B$8,$B$10:$B$11) -> 0.085714286 | D8: CPI | E8: 100 | F8: =100*(1+(Inputs!B6-0.025)) -> 101.3 | G8: =+(F8-E8)/E8 -> 0.013
A9: Royalties (2.5% Revenue) | D9: Gold AUD Price
A10: Sustaining Capital | B10: 350 | C10: =+B10/SUM($B$3:$B$8,$B$10:$B$11) -> 0.16666667 | D10: Capex Inflation Index | E10: 100 | F10: 100 | G10: =+(F10-E10)/E10 -> 0
A11: Corporate & Other | B11: 70 | C11: =+B11/SUM($B$3:$B$8,$B$10:$B$11) -> 0.033333333 | D11: CPI | E11: =+E8 -> 100 | F11: =+F8 -> 101.3 | G11: =+(F11-E11)/E11 -> 0.013
C12: =SUM(C3:C11) -> 1
